dominion_grpc_client/__init__.py
dominion_grpc_client/client.py
dominion_grpc_client-0.15.0.dist-info/LICENSE
dominion_grpc_client-0.15.0.dist-info/METADATA
dominion_grpc_client-0.15.0.dist-info/WHEEL
dominion_grpc_client-0.15.0.dist-info/top_level.txt
dominion_grpc_client-0.15.0.dist-info/RECORD
