Metadata-Version: 2.1
Name: dominion-grpc-client
Version: 0.15.0
Summary: Dominion gRPC client library
Home-page: https://github.com/the-gigi/dominion-grpc-client-py
Author: Gigi Sayfan
Author-email: the.gigi@gmail.com
License: MIT
Platform: UNKNOWN
Requires-Python: >=3.8
